[{"additionalProperties": false, "description": "Hook for changing the mode of a path or paths.", "properties": {"hook_name": {"default": "chmod", "title": "Hook Name", "type": "string"}, "help": {"default": null, "description": "A string to display when calling with the `help` argument.", "title": "Help", "type": "string"}, "render_by_default": {"default": null, "description": "A list of string fields to wrap with jinja braces and render by default.", "items": {}, "title": "Render By Default", "type": "array"}, "render_exclude": {"default": null, "description": "A list of field names to not render.", "items": {}, "title": "Render Exclude", "type": "array"}, "is_public": {"default": null, "description": "A boolean if hook is public / callable from outside the provider).", "title": "Is Public", "type": "boolean"}, "skip_output": {"default": false, "description": "A flag to skip the output and not set the key. Can also be set within a hook call.", "title": "Skip Output", "type": "boolean"}, "args": {"default": ["path", "mode"], "items": {}, "title": "Args", "type": "array"}, "kwargs": {"default": null, "description": "A field name of type dict to map additional arguments to.", "title": "Kwargs", "type": "string"}, "path": {"anyOf": [{"type": "string"}, {"items": {}, "type": "array"}], "description": "String or list of paths, either directories or files.", "title": "Path"}, "mode": {"description": "The mode to write to the files. See python's os package [chmod](https://docs.python.org/3/library/os.html#os.chmod) for more details.", "title": "Mode", "type": "string"}}, "required": ["path", "mode"], "title": "ChmodHook", "type": "object"}, {"additionalProperties": false, "description": "Hook for changing the ownership of a file with shutil.", "properties": {"hook_name": {"default": "chown", "title": "Hook Name", "type": "string"}, "help": {"default": null, "description": "A string to display when calling with the `help` argument.", "title": "Help", "type": "string"}, "render_by_default": {"default": null, "description": "A list of string fields to wrap with jinja braces and render by default.", "items": {}, "title": "Render By Default", "type": "array"}, "render_exclude": {"default": null, "description": "A list of field names to not render.", "items": {}, "title": "Render Exclude", "type": "array"}, "is_public": {"default": null, "description": "A boolean if hook is public / callable from outside the provider).", "title": "Is Public", "type": "boolean"}, "skip_output": {"default": false, "description": "A flag to skip the output and not set the key. Can also be set within a hook call.", "title": "Skip Output", "type": "boolean"}, "args": {"default": ["path", "user", "group"], "items": {}, "title": "Args", "type": "array"}, "kwargs": {"default": null, "description": "A field name of type dict to map additional arguments to.", "title": "Kwargs", "type": "string"}, "path": {"anyOf": [{"type": "string"}, {"items": {}, "type": "array"}], "description": "String or list of paths, either directories or files.", "title": "Path"}, "user": {"description": "The user to assign ownership.", "title": "User", "type": "string"}, "group": {"description": "The group to assign ownership.", "title": "Group", "type": "string"}}, "required": ["path", "user", "group"], "title": "ChownHook", "type": "object"}, {"additionalProperties": false, "description": "Hook coying a file/files or directory/directories to a location.", "properties": {"hook_name": {"default": "copy", "title": "Hook Name", "type": "string"}, "help": {"default": null, "description": "A string to display when calling with the `help` argument.", "title": "Help", "type": "string"}, "render_by_default": {"default": null, "description": "A list of string fields to wrap with jinja braces and render by default.", "items": {}, "title": "Render By Default", "type": "array"}, "render_exclude": {"default": null, "description": "A list of field names to not render.", "items": {}, "title": "Render Exclude", "type": "array"}, "is_public": {"default": null, "description": "A boolean if hook is public / callable from outside the provider).", "title": "Is Public", "type": "boolean"}, "skip_output": {"default": false, "description": "A flag to skip the output and not set the key. Can also be set within a hook call.", "title": "Skip Output", "type": "boolean"}, "args": {"default": ["src", "dst"], "items": {}, "title": "Args", "type": "array"}, "kwargs": {"default": null, "description": "A field name of type dict to map additional arguments to.", "title": "Kwargs", "type": "string"}, "src": {"anyOf": [{"items": {}, "type": "array"}, {"type": "string"}], "description": "String or list of sources, either a directories or files", "title": "Src"}, "dst": {"description": "The destination to copy to.", "title": "Dst", "type": "string"}, "create_path": {"default": true, "title": "Create Path", "type": "boolean"}}, "required": ["src", "dst"], "title": "CopyHook", "type": "object"}, {"additionalProperties": false, "description": "Hook to create an empty file - like touch.", "properties": {"hook_name": {"default": "create_file", "title": "Hook Name", "type": "string"}, "help": {"default": null, "description": "A string to display when calling with the `help` argument.", "title": "Help", "type": "string"}, "render_by_default": {"default": null, "description": "A list of string fields to wrap with jinja braces and render by default.", "items": {}, "title": "Render By Default", "type": "array"}, "render_exclude": {"default": null, "description": "A list of field names to not render.", "items": {}, "title": "Render Exclude", "type": "array"}, "is_public": {"default": null, "description": "A boolean if hook is public / callable from outside the provider).", "title": "Is Public", "type": "boolean"}, "skip_output": {"default": false, "description": "A flag to skip the output and not set the key. Can also be set within a hook call.", "title": "Skip Output", "type": "boolean"}, "args": {"default": ["path"], "items": {}, "title": "Args", "type": "array"}, "kwargs": {"default": null, "description": "A field name of type dict to map additional arguments to.", "title": "Kwargs", "type": "string"}, "path": {"anyOf": [{"type": "string"}, {"items": {}, "type": "array"}], "description": "String or list of paths to create files at.", "title": "Path"}}, "required": ["path"], "title": "CreateFileHook", "type": "object"}, {"additionalProperties": false, "description": "Hook to read or write a file.", "properties": {"hook_name": {"default": "file", "title": "Hook Name", "type": "string"}, "help": {"default": null, "description": "A string to display when calling with the `help` argument.", "title": "Help", "type": "string"}, "render_by_default": {"default": null, "description": "A list of string fields to wrap with jinja braces and render by default.", "items": {}, "title": "Render By Default", "type": "array"}, "render_exclude": {"default": null, "description": "A list of field names to not render.", "items": {}, "title": "Render Exclude", "type": "array"}, "is_public": {"default": null, "description": "A boolean if hook is public / callable from outside the provider).", "title": "Is Public", "type": "boolean"}, "skip_output": {"default": false, "description": "A flag to skip the output and not set the key. Can also be set within a hook call.", "title": "Skip Output", "type": "boolean"}, "args": {"default": ["path", "contents"], "items": {}, "title": "Args", "type": "array"}, "kwargs": {"default": null, "description": "A field name of type dict to map additional arguments to.", "title": "Kwargs", "type": "string"}, "path": {"description": "Path to read a file or write file if contents are given.", "title": "Path", "type": "string"}, "contents": {"default": null, "description": "If writing to file, the contents to write.", "title": "Contents"}}, "required": ["path"], "title": "FileHook", "type": "object"}, {"additionalProperties": false, "description": "Hook  for moving a directory or directories to a location.", "properties": {"hook_name": {"default": "move", "title": "Hook Name", "type": "string"}, "help": {"default": null, "description": "A string to display when calling with the `help` argument.", "title": "Help", "type": "string"}, "render_by_default": {"default": null, "description": "A list of string fields to wrap with jinja braces and render by default.", "items": {}, "title": "Render By Default", "type": "array"}, "render_exclude": {"default": null, "description": "A list of field names to not render.", "items": {}, "title": "Render Exclude", "type": "array"}, "is_public": {"default": null, "description": "A boolean if hook is public / callable from outside the provider).", "title": "Is Public", "type": "boolean"}, "skip_output": {"default": false, "description": "A flag to skip the output and not set the key. Can also be set within a hook call.", "title": "Skip Output", "type": "boolean"}, "args": {"default": ["src", "dst"], "items": {}, "title": "Args", "type": "array"}, "kwargs": {"default": null, "description": "A field name of type dict to map additional arguments to.", "title": "Kwargs", "type": "string"}, "src": {"anyOf": [{"items": {}, "type": "array"}, {"type": "string"}], "description": "String or list of sources, either directories or files", "title": "Src"}, "dst": {"description": "String for path to copy to", "title": "Dst", "type": "string"}, "create_path": {"default": true, "description": "Boolean to create the directory path if it does not exist.", "title": "Create Path", "type": "boolean"}}, "required": ["src", "dst"], "title": "MoveHook", "type": "object"}, {"additionalProperties": false, "description": "Hook for removing a directory or directories.", "properties": {"hook_name": {"default": "remove", "title": "Hook Name", "type": "string"}, "help": {"default": null, "description": "A string to display when calling with the `help` argument.", "title": "Help", "type": "string"}, "render_by_default": {"default": null, "description": "A list of string fields to wrap with jinja braces and render by default.", "items": {}, "title": "Render By Default", "type": "array"}, "render_exclude": {"default": null, "description": "A list of field names to not render.", "items": {}, "title": "Render Exclude", "type": "array"}, "is_public": {"default": null, "description": "A boolean if hook is public / callable from outside the provider).", "title": "Is Public", "type": "boolean"}, "skip_output": {"default": false, "description": "A flag to skip the output and not set the key. Can also be set within a hook call.", "title": "Skip Output", "type": "boolean"}, "args": {"default": ["path"], "items": {}, "title": "Args", "type": "array"}, "kwargs": {"default": null, "description": "A field name of type dict to map additional arguments to.", "title": "Kwargs", "type": "string"}, "path": {"anyOf": [{"items": {}, "type": "array"}, {"type": "string"}], "description": "String or list of paths to remove.", "title": "Path"}}, "required": ["path"], "title": "RemoveHook", "type": "object"}, {"additionalProperties": false, "description": "Hook for shredding file/files.", "properties": {"hook_name": {"default": "shred", "title": "Hook Name", "type": "string"}, "help": {"default": null, "description": "A string to display when calling with the `help` argument.", "title": "Help", "type": "string"}, "render_by_default": {"default": null, "description": "A list of string fields to wrap with jinja braces and render by default.", "items": {}, "title": "Render By Default", "type": "array"}, "render_exclude": {"default": null, "description": "A list of field names to not render.", "items": {}, "title": "Render Exclude", "type": "array"}, "is_public": {"default": null, "description": "A boolean if hook is public / callable from outside the provider).", "title": "Is Public", "type": "boolean"}, "skip_output": {"default": false, "description": "A flag to skip the output and not set the key. Can also be set within a hook call.", "title": "Skip Output", "type": "boolean"}, "args": {"default": ["src", "passes"], "items": {}, "title": "Args", "type": "array"}, "kwargs": {"default": null, "description": "A field name of type dict to map additional arguments to.", "title": "Kwargs", "type": "string"}, "src": {"anyOf": [{"items": {}, "type": "array"}, {"type": "string"}], "description": "String or list of sources, either directories or files", "title": "Src"}, "passes": {"default": 10, "description": "The number of passes to overwrite the location.", "title": "Passes", "type": "integer"}}, "required": ["src"], "title": "ShredHook", "type": "object"}, {"additionalProperties": false, "description": "Wrapper of shutil.which -> posix which.", "properties": {"hook_name": {"default": "which", "title": "Hook Name", "type": "string"}, "help": {"default": null, "description": "A string to display when calling with the `help` argument.", "title": "Help", "type": "string"}, "render_by_default": {"default": null, "description": "A list of string fields to wrap with jinja braces and render by default.", "items": {}, "title": "Render By Default", "type": "array"}, "render_exclude": {"default": null, "description": "A list of field names to not render.", "items": {}, "title": "Render Exclude", "type": "array"}, "is_public": {"default": null, "description": "A boolean if hook is public / callable from outside the provider).", "title": "Is Public", "type": "boolean"}, "skip_output": {"default": false, "description": "A flag to skip the output and not set the key. Can also be set within a hook call.", "title": "Skip Output", "type": "boolean"}, "args": {"default": ["path"], "items": {}, "title": "Args", "type": "array"}, "kwargs": {"default": null, "description": "A field name of type dict to map additional arguments to.", "title": "Kwargs", "type": "string"}, "path": {"description": "String path run `which` against.", "title": "Path", "type": "string"}}, "required": ["path"], "title": "WhichHook", "type": "object"}, {"additionalProperties": false, "description": "Hook for reading a section of a document.", "properties": {"hook_name": {"default": "read_section", "title": "Hook Name", "type": "string"}, "help": {"default": null, "description": "A string to display when calling with the `help` argument.", "title": "Help", "type": "string"}, "render_by_default": {"default": null, "description": "A list of string fields to wrap with jinja braces and render by default.", "items": {}, "title": "Render By Default", "type": "array"}, "render_exclude": {"default": null, "description": "A list of field names to not render.", "items": {}, "title": "Render Exclude", "type": "array"}, "is_public": {"default": null, "description": "A boolean if hook is public / callable from outside the provider).", "title": "Is Public", "type": "boolean"}, "skip_output": {"default": false, "description": "A flag to skip the output and not set the key. Can also be set within a hook call.", "title": "Skip Output", "type": "boolean"}, "args": {"default": ["document", "start", "end"], "items": {}, "title": "Args", "type": "array"}, "kwargs": {"default": null, "description": "A field name of type dict to map additional arguments to.", "title": "Kwargs", "type": "string"}, "document": {"description": "Path to a document to render a section of.", "title": "Document", "type": "string"}, "start": {"default": "--start--", "description": "Marker generally in some kind of comment to begin reading from.", "title": "Start", "type": "string"}, "end": {"default": "--end--", "description": "Marker generally in some kind of comment to end reading from.", "title": "End", "type": "string"}}, "required": ["document"], "title": "UpdateSectionHook", "type": "object"}, {"additionalProperties": false, "description": "Hook to unzip a file.", "properties": {"hook_name": {"default": "unzipfile", "title": "Hook Name", "type": "string"}, "help": {"default": null, "description": "A string to display when calling with the `help` argument.", "title": "Help", "type": "string"}, "render_by_default": {"default": null, "description": "A list of string fields to wrap with jinja braces and render by default.", "items": {}, "title": "Render By Default", "type": "array"}, "render_exclude": {"default": null, "description": "A list of field names to not render.", "items": {}, "title": "Render Exclude", "type": "array"}, "is_public": {"default": null, "description": "A boolean if hook is public / callable from outside the provider).", "title": "Is Public", "type": "boolean"}, "skip_output": {"default": false, "description": "A flag to skip the output and not set the key. Can also be set within a hook call.", "title": "Skip Output", "type": "boolean"}, "args": {"default": [], "description": "A list of fields map arguments. See [docs]() for details.", "items": {}, "title": "Args", "type": "array"}, "kwargs": {"default": null, "description": "A field name of type dict to map additional arguments to.", "title": "Kwargs", "type": "string"}, "input": {"description": "Input path", "title": "Input", "type": "string"}, "output": {"default": ".", "description": "Output path, default to current directory", "title": "Output", "type": "string"}}, "required": ["input"], "title": "UnzipHook", "type": "object"}, {"additionalProperties": false, "description": "Hook to zip a file or directory.", "properties": {"hook_name": {"default": "zipfile", "title": "Hook Name", "type": "string"}, "help": {"default": null, "description": "A string to display when calling with the `help` argument.", "title": "Help", "type": "string"}, "render_by_default": {"default": null, "description": "A list of string fields to wrap with jinja braces and render by default.", "items": {}, "title": "Render By Default", "type": "array"}, "render_exclude": {"default": null, "description": "A list of field names to not render.", "items": {}, "title": "Render Exclude", "type": "array"}, "is_public": {"default": null, "description": "A boolean if hook is public / callable from outside the provider).", "title": "Is Public", "type": "boolean"}, "skip_output": {"default": false, "description": "A flag to skip the output and not set the key. Can also be set within a hook call.", "title": "Skip Output", "type": "boolean"}, "args": {"default": [], "description": "A list of fields map arguments. See [docs]() for details.", "items": {}, "title": "Args", "type": "array"}, "kwargs": {"default": null, "description": "A field name of type dict to map additional arguments to.", "title": "Kwargs", "type": "string"}, "input": {"description": "Input path", "title": "Input", "type": "string"}, "output": {"description": "Output path", "title": "Output", "type": "string"}}, "required": ["input", "output"], "title": "ZipHook", "type": "object"}]